ecnuopenapi/__init__.py
ecnuopenapi/api.py
ecnuopenapi/model.py
ecnuopenapi/oauth_init.py
ecnuopenapi/parse.py
ecnuopenapi/sync.py
ecnu_openapi_sdk_python-1.0.0.dist-info/LICENSE
ecnu_openapi_sdk_python-1.0.0.dist-info/METADATA
ecnu_openapi_sdk_python-1.0.0.dist-info/WHEEL
ecnu_openapi_sdk_python-1.0.0.dist-info/top_level.txt
ecnu_openapi_sdk_python-1.0.0.dist-info/RECORD
