Metadata-Version: 2.1
Name: ecnu-openapi-sdk-python
Version: 1.0.0
Summary: ecnu-openapi-sdk-python
Home-page: https://github.com/ECNU/ecnu-openapi-sdk-python
Author: ECNU
Author-email: dataservice@ecnu.edu.cn
License: UNKNOWN
Platform: UNKNOWN
Classifier: Programming Language :: Python :: 3
Classifier: License :: OSI Approved :: Apache Software License
Classifier: Operating System :: OS Independent
Requires-Dist: oauthlib ==3.2.0
Requires-Dist: psutil ==5.9.4
Requires-Dist: Requests ==2.31.0
Requires-Dist: requests-oauthlib ==1.3.1
Requires-Dist: SQLAlchemy ==2.0.22
Requires-Dist: psycopg2
Requires-Dist: pymssql
Requires-Dist: pymysql
Requires-Dist: cx-oracle
